phipkit/__init__.py
phipkit/antigen_analysis.py
phipkit/blast.py
phipkit/call_antigens.py
phipkit/call_hits.py
phipkit/common.py
phipkit/plot_antigens.py
phipkit/score.py
phipkit-0.0.1.dist-info/LICENSE
phipkit-0.0.1.dist-info/METADATA
phipkit-0.0.1.dist-info/WHEEL
phipkit-0.0.1.dist-info/entry_points.txt
phipkit-0.0.1.dist-info/top_level.txt
phipkit-0.0.1.dist-info/RECORD
