Metadata-Version: 2.1
Name: phipkit
Version: 0.0.1
Summary: PhIP-seq analysis library
Home-page: https://github.com/openvax/phipkit
Author: Tim O'Donnell
Author-email: timodonnell@gmail.com
License: UNKNOWN
Project-URL: Bug Tracker, https://github.com/openvax/phipkit/issues
Platform: UNKNOWN
Classifier: Programming Language :: Python :: 3
Classifier: Topic :: Scientific/Engineering :: Bio-Informatics
Classifier: License :: OSI Approved :: MIT License
Classifier: Operating System :: OS Independent
Requires-Python: >=3.3
Requires-Dist: pandas
Requires-Dist: dna-features-viewer
Requires-Dist: tqdm
Requires-Dist: statsmodels
Requires-Dist: seaborn
